qtask_py/__init__.py
qtask_py/config.py
qtask_py/orchestrator.py
qtask_py/publisher.py
qtask_py/qtask.py
qtask_py/utils.py
qtask_py/worker.py
qtask_py-0.1.5.dist-info/LICENSE
qtask_py-0.1.5.dist-info/METADATA
qtask_py-0.1.5.dist-info/WHEEL
qtask_py-0.1.5.dist-info/RECORD
