Metadata-Version: 2.3
Name: qtask-py
Version: 0.1.5
Summary: 
License: MIT
Author: Rafael Garcia Suarez
Author-email: rafaeljosegarciasuarez@gmail.com
Requires-Python: >=3.10,<4.0
Classifier: License :: OSI Approved :: MIT License
Classifier: Programming Language :: Python :: 3
Classifier: Programming Language :: Python :: 3.10
Classifier: Programming Language :: Python :: 3.11
Classifier: Programming Language :: Python :: 3.12
Classifier: Programming Language :: Python :: 3.13
Requires-Dist: redis (>=5.0.0,<6.0.0)
